fff/__init__.py
fff/cli.py
fff_formfieldfinder-1.0.2.dist-info/licenses/LICENSE
fff_formfieldfinder-1.0.2.dist-info/METADATA
fff_formfieldfinder-1.0.2.dist-info/WHEEL
fff_formfieldfinder-1.0.2.dist-info/entry_points.txt
fff_formfieldfinder-1.0.2.dist-info/top_level.txt
fff_formfieldfinder-1.0.2.dist-info/RECORD
