Metadata-Version: 2.4
Name: fff-formfieldfinder
Version: 1.0.2
Summary: Form Field Finder: Extracts login fields and form action for fuzzing
Home-page: https://github.com/Ph4nt01/FFF-FormFieldFinder
Author: [Ph4nt01]
Author-email: ph4nt0.84@gmail.com
Classifier: Programming Language :: Python :: 3
Classifier: License :: OSI Approved :: MIT License
Requires-Python: >=3.7
License-File: LICENSE
Requires-Dist: beautifulsoup4
Requires-Dist: requests
Requires-Dist: colorama
Dynamic: author
Dynamic: author-email
Dynamic: classifier
Dynamic: home-page
Dynamic: license-file
Dynamic: requires-dist
Dynamic: requires-python
Dynamic: summary
